Metadata-Version: 2.2
Name: fyle-djangoq2
Version: 2.0.1
Summary: Python SDK for Django Q2
Home-page: https://github.com/fylein/django-q2.git
Author: Rushikesh
Author-email: rushikesh.t@fyle.in
License: MIT
Keywords: django-q2django-q,fyle,queue,python,sdk
Classifier: Topic :: Internet :: WWW/HTTP
Classifier: Intended Audience :: Developers
Classifier: Programming Language :: Python :: 3
Classifier: License :: OSI Approved :: MIT License
Classifier: Operating System :: OS Independent
License-File: LICENSE
Dynamic: author
Dynamic: author-email
Dynamic: classifier
Dynamic: description
Dynamic: description-content-type
Dynamic: home-page
Dynamic: keywords
Dynamic: license
Dynamic: summary
